README.md
func_adl/__init__.py
func_adl/event_dataset.py
func_adl/functions.py
func_adl/object_stream.py
func_adl/type_based_replacement.py
func_adl/util_ast.py
func_adl/util_types.py
func_adl/version.txt
func_adl/ast/__init__.py
func_adl/ast/aggregate_shortcuts.py
func_adl/ast/ast_hash.py
func_adl/ast/call_stack.py
func_adl/ast/func_adl_ast_utils.py
func_adl/ast/function_simplifier.py
func_adl/ast/meta_data.py
func_adl/ast/syntatic_sugar.py
func_adl-3.4.2.dist-info/METADATA
func_adl-3.4.2.dist-info/WHEEL
func_adl-3.4.2.dist-info/licenses/LICENSE
func_adl-3.4.2.dist-info/RECORD
