Metadata-Version: 2.4
Name: func_adl
Version: 3.4.2
Summary: Functional Analysis Description Language Base Package
Author-email: "G. Watts (IRIS-HEP/UW Seattle)" <gwatts@uw.edu>
Maintainer-email: "Gordon Watts (IRIS-HEP/UW Seattle)" <gwatts@uw.edu>
License: MIT
License-File: LICENSE
Classifier: Development Status :: 5 - Production/Stable
Classifier: Intended Audience :: Developers
Classifier: Intended Audience :: Information Technology
Classifier: Programming Language :: Python
Classifier: Programming Language :: Python :: 3.9
Classifier: Programming Language :: Python :: 3.10
Classifier: Programming Language :: Python :: 3.11
Classifier: Programming Language :: Python :: 3.12
Classifier: Programming Language :: Python :: 3.13
Classifier: Topic :: Software Development
Classifier: Topic :: Utilities
Requires-Python: >=3.9
Requires-Dist: make-it-sync
Provides-Extra: test
Requires-Dist: astunparse; extra == 'test'
Requires-Dist: black; extra == 'test'
Requires-Dist: coverage; extra == 'test'
Requires-Dist: flake8; extra == 'test'
Requires-Dist: hatch; extra == 'test'
Requires-Dist: isort; extra == 'test'
Requires-Dist: numpy; extra == 'test'
Requires-Dist: pytest; extra == 'test'
Requires-Dist: pytest-asyncio; extra == 'test'
Requires-Dist: pytest-cov; extra == 'test'
Requires-Dist: twine; extra == 'test'
Requires-Dist: wheel; extra == 'test'
